qdf/__init__.py
qdf/base.py
qdf/client.py
qdf/exceptions.py
qdf/models/__init__.py
qdf/models/macro.py
qdf/models/pools.py
qdf/models/rankings.py
qdf_sdk-0.2.1.dist-info/licenses/LICENSE
qdf_sdk-0.2.1.dist-info/METADATA
qdf_sdk-0.2.1.dist-info/WHEEL
qdf_sdk-0.2.1.dist-info/top_level.txt
qdf_sdk-0.2.1.dist-info/RECORD
