Metadata-Version: 2.4
Name: qdf-sdk
Version: 0.2.1
Summary: Python SDK for QuantDeFi Pool Rankings and Analytics API
Home-page: https://github.com/QuantDeFi/qdf-sdk
Author: QuantDeFi
Author-email: QuantDeFi <dev@quantdefi.com>
Maintainer-email: QuantDeFi Team <dev@quantdefi.com>
License: MIT
Project-URL: Homepage, https://quantdefi.com
Project-URL: Documentation, https://docs.quantdefi.com
Project-URL: Repository, https://github.com/QuantDeFi/qdf-sdk
Project-URL: Issues, https://github.com/QuantDeFi/qdf-sdk/issues
Project-URL: Changelog, https://github.com/QuantDeFi/qdf-sdk/blob/main/CHANGELOG.md
Keywords: defi,blockchain,crypto,pools,rankings,analytics,api,sdk,quantdefi
Classifier: Development Status :: 4 - Beta
Classifier: Intended Audience :: Developers
Classifier: Intended Audience :: Financial and Insurance Industry
Classifier: Topic :: Office/Business :: Financial :: Investment
Classifier: Topic :: Software Development :: Libraries :: Python Modules
Classifier: License :: OSI Approved :: MIT License
Classifier: Programming Language :: Python :: 3
Classifier: Programming Language :: Python :: 3.8
Classifier: Programming Language :: Python :: 3.9
Classifier: Programming Language :: Python :: 3.10
Classifier: Programming Language :: Python :: 3.11
Classifier: Programming Language :: Python :: 3.12
Classifier: Operating System :: OS Independent
Classifier: Typing :: Typed
Requires-Python: >=3.8
License-File: LICENSE
Requires-Dist: requests>=2.31.0
Requires-Dist: pydantic>=2.0.0
Requires-Dist: python-dateutil>=2.8.2
Provides-Extra: pandas
Requires-Dist: pandas>=2.0.0; extra == "pandas"
Provides-Extra: dev
Requires-Dist: pytest>=7.4.0; extra == "dev"
Requires-Dist: pytest-asyncio>=0.21.0; extra == "dev"
Requires-Dist: black>=23.7.0; extra == "dev"
Requires-Dist: mypy>=1.4.0; extra == "dev"
Requires-Dist: twine>=3.8.0; extra == "dev"
Requires-Dist: build>=0.10.0; extra == "dev"
Provides-Extra: all
Requires-Dist: pandas>=2.0.0; extra == "all"
Requires-Dist: pytest>=7.4.0; extra == "all"
Requires-Dist: pytest-asyncio>=0.21.0; extra == "all"
Requires-Dist: black>=23.7.0; extra == "all"
Requires-Dist: mypy>=1.4.0; extra == "all"
Dynamic: author
Dynamic: home-page
Dynamic: license-file
Dynamic: requires-python
